{"type": "FeatureCollection", "features": [{"geometry": {"type": "Point", "coordinates": [102.25094968581668, 24.21724173130335]}, "properties": {"name": "Eshan Yi Autonomous County"}, "type": "Feature"}, {"geometry": {"type": "Point", "coordinates": [102.51682111239204, 24.36474471701703]}, "properties": {"name": "Hongta District"}, "type": "Feature"}, {"geometry": {"type": "Point", "coordinates": [102.73930464514474, 24.35349823394039]}, "properties": {"name": "Jiangchuan County"}, "type": "Feature"}, {"geometry": {"type": "Point", "coordinates": [102.66531694236232, 24.106786803823184]}, "properties": {"name": "Tonghai"}, "type": "Feature"}, {"geometry": {"type": "Point", "coordinates": [101.75440476702856, 24.023194748308857]}, "properties": {"name": "Xinping Yi and Dai Autonomous County"}, "type": "Feature"}, {"geometry": {"type": "Point", "coordinates": [102.09444758727352, 24.671003602356095]}, "properties": {"name": "Yimen"}, "type": "Feature"}, {"geometry": {"type": "Point", "coordinates": [101.98242549546836, 23.58981252030403]}, "properties": {"name": "Yuanjiang Hani, Yi and Dai Autonomous County"}, "type": "Feature"}, {"geometry": {"type": "Point", "coordinates": [102.98348739205602, 24.241680101584514]}, "properties": {"name": "Hua County"}, "type": "Feature"}, {"geometry": {"type": "Point", "coordinates": [102.95239996905647, 24.719659831291775]}, "properties": {"name": "Chengjiang County"}, "type": "Feature"}]}